tinyrag/__init__.py
tinyrag/core/__init__.py
tinyrag/core/code_parser.py
tinyrag/core/document_cache.py
tinyrag/core/provider.py
tinyrag/core/structured_response.py
tinyrag/core/text_utils.py
tinyrag/core/tinyrag.py
tinyrag/vector_stores/__init__.py
tinyrag/vector_stores/base.py
tinyrag/vector_stores/chroma_store.py
tinyrag/vector_stores/faiss_store.py
tinyrag/vector_stores/memory_store.py
tinyrag/vector_stores/pickle_store.py
tinyrag-0.3.5.dist-info/licenses/LICENSE
tinyrag-0.3.5.dist-info/METADATA
tinyrag-0.3.5.dist-info/WHEEL
tinyrag-0.3.5.dist-info/top_level.txt
tinyrag-0.3.5.dist-info/RECORD
