Metadata-Version: 2.4
Name: tinyrag
Version: 0.3.5
Summary: A minimal Python library for Retrieval-Augmented Generation with codebase indexing and multiple vector store backends
Home-page: https://github.com/Kenosis01/TinyRag
Author: TinyRag Team
Author-email: TinyRag Team <transformtrails@gmail.com>
Maintainer-email: TinyRag Team <transformtrails@gmail.com>
License: MIT
Project-URL: Homepage, https://github.com/Kenosis01/TinyRag
Project-URL: Documentation, https://github.com/Kenosis01/TinyRag#readme
Project-URL: Repository, https://github.com/Kenosis01/TinyRag.git
Project-URL: Bug Tracker, https://github.com/Kenosis01/TinyRag/issues
Project-URL: Changelog, https://github.com/Kenosis01/TinyRag/blob/main/CHANGELOG.md
Keywords: rag,retrieval,augmented,generation,vector,database,embeddings,similarity,search,nlp,ai,machine-learning,codebase,code-indexing,function-search,code-analysis
Classifier: Development Status :: 4 - Beta
Classifier: Intended Audience :: Developers
Classifier: Intended Audience :: Science/Research
Classifier: License :: OSI Approved :: MIT License
Classifier: Operating System :: OS Independent
Classifier: Programming Language :: Python :: 3
Classifier: Programming Language :: Python :: 3.7
Classifier: Programming Language :: Python :: 3.8
Classifier: Programming Language :: Python :: 3.9
Classifier: Programming Language :: Python :: 3.10
Classifier: Programming Language :: Python :: 3.11
Classifier: Programming Language :: Python :: 3.12
Classifier: Topic :: Scientific/Engineering :: Artificial Intelligence
Classifier: Topic :: Software Development :: Libraries :: Python Modules
Classifier: Topic :: Text Processing :: Linguistic
Requires-Python: >=3.7
License-File: LICENSE
Requires-Dist: sentence-transformers
Requires-Dist: requests
Requires-Dist: numpy
Requires-Dist: faiss-cpu
Requires-Dist: scikit-learn
Requires-Dist: chromadb
Requires-Dist: pdfminer.six>=20221105
Requires-Dist: python-docx>=0.8.11
Provides-Extra: faiss
Requires-Dist: faiss-cpu>=1.7.0; extra == "faiss"
Provides-Extra: chroma
Requires-Dist: chromadb>=0.4.0; extra == "chroma"
Provides-Extra: pickle
Requires-Dist: scikit-learn>=1.0.0; extra == "pickle"
Provides-Extra: docs
Requires-Dist: pdfminer.six>=20221105; extra == "docs"
Requires-Dist: python-docx>=0.8.11; extra == "docs"
Provides-Extra: all
Requires-Dist: faiss-cpu>=1.7.0; extra == "all"
Requires-Dist: chromadb>=0.4.0; extra == "all"
Requires-Dist: scikit-learn>=1.0.0; extra == "all"
Requires-Dist: pdfminer.six>=20221105; extra == "all"
Requires-Dist: python-docx>=0.8.11; extra == "all"
Provides-Extra: dev
Requires-Dist: pytest>=6.0; extra == "dev"
Requires-Dist: pytest-cov>=2.0; extra == "dev"
Requires-Dist: black>=21.0; extra == "dev"
Requires-Dist: flake8>=3.8; extra == "dev"
Requires-Dist: mypy>=0.910; extra == "dev"
Requires-Dist: twine>=3.0; extra == "dev"
Requires-Dist: build>=0.7; extra == "dev"
Dynamic: author
Dynamic: home-page
Dynamic: license-file
Dynamic: requires-python
